sockric/__init__.py
sockric/_client.py
sockric/_events.py
sockric/_packet.py
sockric/_server.py
sockric/_transport.py
sockric/_utils.py
sockric-0.2.1.dist-info/licenses/LICENSE
sockric-0.2.1.dist-info/METADATA
sockric-0.2.1.dist-info/WHEEL
sockric-0.2.1.dist-info/top_level.txt
sockric-0.2.1.dist-info/RECORD
