Metadata-Version: 2.4
Name: sockric
Version: 0.2.1
Summary: A Server/Client extension to the 'socket' library. Developed for personal use.
Author: Luka Jacobsen
License: Creative Commons Attribution-NonCommercial 4.0 International (CC BY-NC 4.0)
Requires-Python: >=3.10
License-File: LICENSE
Dynamic: license-file
